{
    "classes": [
        {
            "className": "desk",
            "methods": [
                {
                    "access": "public",
                    "arguments": [
                        {
                            "name": "num1",
                            "type": "std::vector<int>"
                        }
                    ],
                    "name": "setNum",
                    "returnType": "void"
                },
                {
                    "access": "public",
                    "name": "getNum",
                    "returnType": "std::vector<int>"
                },
                {
                    "access": "public",
                    "name": "getNumRef",
                    "returnType": "int"
                },
                {
                    "access": "public",
                    "name": "touchCard",
                    "returnType": "void"
                },
                {
                    "access": "public",
                    "name": "getP1Hand",
                    "returnType": "std::vector<people::poker>"
                },
                {
                    "access": "public",
                    "name": "getP2Hand",
                    "returnType": "std::vector<people::poker>"
                },
                {
                    "access": "public",
                    "name": "getP3Hand",
                    "returnType": "std::vector<people::poker>"
                }
            ],
            "object": true,
            "qualifiedClassName": "desk",
            "superClasses": [
                {
                    "access": "public",
                    "name": "QObject"
                }
            ]
        }
    ],
    "inputFile": "desk.h",
    "outputRevision": 68
}
